{
  "季节性分析": {
    "1月(冬)": {
      "平均温度": 15.18,
      "最高温度": 22.3,
      "最低温度": 4.1,
      "标准差": 3.73,
      "数据天数": 310
    },
    "2月(冬)": {
      "平均温度": 16.03,
      "最高温度": 24.8,
      "最低温度": 5.9,
      "标准差": 4.06,
      "数据天数": 283
    },
    "3月(春)": {
      "平均温度": 19.66,
      "最高温度": 27.0,
      "最低温度": 9.5,
      "标准差": 3.47,
      "数据天数": 310
    },
    "4月(春)": {
      "平均温度": 23.0,
      "最高温度": 27.9,
      "最低温度": 13.7,
      "标准差": 2.78,
      "数据天数": 300
    },
    "5月(春)": {
      "平均温度": 25.89,
      "最高温度": 31.3,
      "最低温度": 17.2,
      "标准差": 2.2,
      "数据天数": 310
    },
    "6月(夏)": {
      "平均温度": 27.72,
      "最高温度": 30.5,
      "最低温度": 24.6,
      "标准差": 1.27,
      "数据天数": 300
    },
    "7月(夏)": {
      "平均温度": 28.89,
      "最高温度": 32.6,
      "最低温度": 25.2,
      "标准差": 1.46,
      "数据天数": 310
    },
    "8月(夏)": {
      "平均温度": 28.13,
      "最高温度": 31.8,
      "最低温度": 25.0,
      "标准差": 1.23,
      "数据天数": 310
    },
    "9月(秋)": {
      "平均温度": 27.56,
      "最高温度": 32.4,
      "最低温度": 20.4,
      "标准差": 1.48,
      "数据天数": 300
    },
    "10月(秋)": {
      "平均温度": 24.5,
      "最高温度": 30.7,
      "最低温度": 17.1,
      "标准差": 2.67,
      "数据天数": 310
    },
    "11月(秋)": {
      "平均温度": 20.59,
      "最高温度": 25.9,
      "最低温度": 11.6,
      "标准差": 3.28,
      "数据天数": 300
    },
    "12月(冬)": {
      "平均温度": 15.7,
      "最高温度": 23.9,
      "最低温度": 6.0,
      "标准差": 3.55,
      "数据天数": 310
    }
  },
  "年度趋势": {
    "2016": {
      "年平均温度": 22.52,
      "最高温度": 32.0,
      "最低温度": 4.1,
      "温度标准差": 6.17,
      "数据天数": 366
    },
    "2017": {
      "年平均温度": 22.39,
      "最高温度": 31.2,
      "最低温度": 8.5,
      "温度标准差": 5.59,
      "数据天数": 365
    },
    "2018": {
      "年平均温度": 22.29,
      "最高温度": 30.4,
      "最低温度": 4.9,
      "温度标准差": 5.89,
      "数据天数": 365
    },
    "2019": {
      "年平均温度": 23.15,
      "最高温度": 31.3,
      "最低温度": 7.7,
      "温度标准差": 5.11,
      "数据天数": 365
    },
    "2020": {
      "年平均温度": 23.02,
      "最高温度": 32.6,
      "最低温度": 7.9,
      "温度标准差": 5.47,
      "数据天数": 366
    },
    "2021": {
      "年平均温度": 23.23,
      "最高温度": 31.1,
      "最低温度": 6.5,
      "温度标准差": 5.57,
      "数据天数": 365
    },
    "2022": {
      "年平均温度": 22.3,
      "最高温度": 32.3,
      "最低温度": 5.9,
      "温度标准差": 6.14,
      "数据天数": 365
    },
    "2023": {
      "年平均温度": 22.86,
      "最高温度": 32.3,
      "最低温度": 7.1,
      "温度标准差": 5.53,
      "数据天数": 365
    },
    "2024": {
      "年平均温度": 22.93,
      "最高温度": 32.5,
      "最低温度": 4.8,
      "温度标准差": 5.62,
      "数据天数": 366
    },
    "2025": {
      "年平均温度": 22.97,
      "最高温度": 32.4,
      "最低温度": 10.1,
      "温度标准差": 5.49,
      "数据天数": 365
    },
    "趋势分析": {
      "前半期平均": 22.67,
      "后半期平均": 22.86,
      "温度变化": 0.18,
      "变化率": 0.81
    }
  },
  "极端事件": {
    "极端高温日": [],
    "极端低温日": [
      {
        "日期": "2016-01-24",
        "平均温度": 4.1,
        "最低温度": 2.6
      },
      {
        "日期": "2024-01-23",
        "平均温度": 4.8,
        "最低温度": 2.8
      },
      {
        "日期": "2018-01-30",
        "平均温度": 4.9,
        "最低温度": 3.7
      },
      {
        "日期": "2016-01-25",
        "平均温度": 5.1,
        "最低温度": 1.9
      },
      {
        "日期": "2024-01-24",
        "平均温度": 5.4,
        "最低温度": 2.0
      },
      {
        "日期": "2018-01-29",
        "平均温度": 5.5,
        "最低温度": 4.0
      },
      {
        "日期": "2018-01-31",
        "平均温度": 5.7,
        "最低温度": 4.8
      },
      {
        "日期": "2016-01-23",
        "平均温度": 5.8,
        "最低温度": 5.3
      },
      {
        "日期": "2016-01-26",
        "平均温度": 5.9,
        "最低温度": 3.5
      },
      {
        "日期": "2022-02-21",
        "平均温度": 5.9,
        "最低温度": 4.7
      }
    ],
    "大温差日": [
      {
        "日期": "2016-02-08",
        "最高温度": 19.5,
        "最低温度": 3.5,
        "日温差": 16.0
      },
      {
        "日期": "2016-02-29",
        "最高温度": 24.4,
        "最低温度": 8.6,
        "日温差": 15.8
      },
      {
        "日期": "2016-02-09",
        "最高温度": 20.8,
        "最低温度": 5.2,
        "日温差": 15.6
      }
    ]
  },
  "季度对比": {
    "2015-Q1(冬)": {
      "平均温度": 16.87,
      "最高温度": 21.3,
      "最低温度": 11.4,
      "天数": 31
    },
    "2016-Q1(冬)": {
      "平均温度": 14.1,
      "最高温度": 22.8,
      "最低温度": 4.1,
      "天数": 91
    },
    "2016-Q2(春)": {
      "平均温度": 22.68,
      "最高温度": 29.1,
      "最低温度": 9.8,
      "天数": 92
    },
    "2016-Q3(夏)": {
      "平均温度": 28.47,
      "最高温度": 32.0,
      "最低温度": 25.3,
      "天数": 92
    },
    "2016-Q4(秋)": {
      "平均温度": 24.08,
      "最高温度": 30.5,
      "最低温度": 11.6,
      "天数": 91
    },
    "2017-Q1(冬)": {
      "平均温度": 15.73,
      "最高温度": 23.0,
      "最低温度": 6.0,
      "天数": 90
    },
    "2017-Q2(春)": {
      "平均温度": 22.04,
      "最高温度": 27.9,
      "最低温度": 13.9,
      "天数": 92
    },
    "2017-Q3(夏)": {
      "平均温度": 28.02,
      "最高温度": 31.2,
      "最低温度": 25.0,
      "天数": 92
    },
    "2017-Q4(秋)": {
      "平均温度": 23.8,
      "最高温度": 29.7,
      "最低温度": 11.7,
      "天数": 91
    },
    "2018-Q1(冬)": {
      "平均温度": 15.31,
      "最高温度": 23.6,
      "最低温度": 4.9,
      "天数": 90
    },
    "2018-Q2(春)": {
      "平均温度": 23.2,
      "最高温度": 30.4,
      "最低温度": 11.8,
      "天数": 92
    },
    "2018-Q3(夏)": {
      "平均温度": 27.79,
      "最高温度": 29.6,
      "最低温度": 25.1,
      "天数": 92
    },
    "2018-Q4(秋)": {
      "平均温度": 23.35,
      "最高温度": 30.2,
      "最低温度": 16.4,
      "天数": 91
    },
    "2019-Q1(冬)": {
      "平均温度": 15.93,
      "最高温度": 22.1,
      "最低温度": 7.7,
      "天数": 90
    },
    "2019-Q2(春)": {
      "平均温度": 22.77,
      "最高温度": 29.6,
      "最低温度": 14.3,
      "天数": 92
    },
    "2019-Q3(夏)": {
      "平均温度": 28.35,
      "最高温度": 31.3,
      "最低温度": 25.8,
      "天数": 92
    },
    "2019-Q4(秋)": {
      "平均温度": 24.66,
      "最高温度": 29.3,
      "最低温度": 15.1,
      "天数": 91
    },
    "2020-Q1(冬)": {
      "平均温度": 16.55,
      "最高温度": 22.7,
      "最低温度": 7.9,
      "天数": 91
    },
    "2020-Q2(春)": {
      "平均温度": 22.82,
      "最高温度": 29.9,
      "最低温度": 14.8,
      "天数": 92
    },
    "2020-Q3(夏)": {
      "平均温度": 28.82,
      "最高温度": 32.6,
      "最低温度": 25.8,
      "天数": 92
    },
    "2020-Q4(秋)": {
      "平均温度": 24.09,
      "最高温度": 30.3,
      "最低温度": 15.6,
      "天数": 91
    },
    "2021-Q1(冬)": {
      "平均温度": 15.37,
      "最高温度": 22.3,
      "最低温度": 6.5,
      "天数": 90
    },
    "2021-Q2(春)": {
      "平均温度": 24.31,
      "最高温度": 30.1,
      "最低温度": 16.3,
      "天数": 92
    },
    "2021-Q3(夏)": {
      "平均温度": 28.35,
      "最高温度": 31.1,
      "最低温度": 25.5,
      "天数": 92
    },
    "2021-Q4(秋)": {
      "平均温度": 23.81,
      "最高温度": 30.8,
      "最低温度": 14.7,
      "天数": 91
    },
    "2022-Q1(冬)": {
      "平均温度": 14.51,
      "最高温度": 23.9,
      "最低温度": 5.9,
      "天数": 90
    },
    "2022-Q2(春)": {
      "平均温度": 22.25,
      "最高温度": 28.1,
      "最低温度": 13.7,
      "天数": 92
    },
    "2022-Q3(夏)": {
      "平均温度": 28.15,
      "最高温度": 32.3,
      "最低温度": 24.7,
      "天数": 92
    },
    "2022-Q4(秋)": {
      "平均温度": 25.11,
      "最高温度": 29.9,
      "最低温度": 16.6,
      "天数": 91
    },
    "2023-Q1(冬)": {
      "平均温度": 15.85,
      "最高温度": 22.1,
      "最低温度": 7.9,
      "天数": 90
    },
    "2023-Q2(春)": {
      "平均温度": 22.99,
      "最高温度": 31.3,
      "最低温度": 15.4,
      "天数": 92
    },
    "2023-Q3(夏)": {
      "平均温度": 28.39,
      "最高温度": 32.3,
      "最低温度": 25.8,
      "天数": 92
    },
    "2023-Q4(秋)": {
      "平均温度": 24.02,
      "最高温度": 29.0,
      "最低温度": 15.3,
      "天数": 91
    },
    "2024-Q1(冬)": {
      "平均温度": 16.54,
      "最高温度": 24.8,
      "最低温度": 4.8,
      "天数": 91
    },
    "2024-Q2(春)": {
      "平均温度": 23.05,
      "最高温度": 27.3,
      "最低温度": 9.5,
      "天数": 92
    },
    "2024-Q3(夏)": {
      "平均温度": 28.24,
      "最高温度": 32.5,
      "最低温度": 24.6,
      "天数": 92
    },
    "2024-Q4(秋)": {
      "平均温度": 24.54,
      "最高温度": 29.8,
      "最低温度": 15.3,
      "天数": 91
    },
    "2025-Q1(冬)": {
      "平均温度": 16.07,
      "最高温度": 20.8,
      "最低温度": 10.3,
      "天数": 59
    },
    "2025-Q2(春)": {
      "平均温度": 22.39,
      "最高温度": 27.9,
      "最低温度": 10.1,
      "天数": 92
    },
    "2025-Q3(夏)": {
      "平均温度": 27.96,
      "最高温度": 30.7,
      "最低温度": 24.8,
      "天数": 92
    },
    "2025-Q4(秋)": {
      "平均温度": 24.74,
      "最高温度": 32.4,
      "最低温度": 12.7,
      "天数": 91
    }
  },
  "能源需求": {
    "2016": {
      "供暖需求日数": 13,
      "制冷需求日数": 154,
      "舒适日数": 198
    },
    "2017": {
      "供暖需求日数": 4,
      "制冷需求日数": 137,
      "舒适日数": 224
    },
    "2018": {
      "供暖需求日数": 17,
      "制冷需求日数": 129,
      "舒适日数": 219
    },
    "2019": {
      "供暖需求日数": 2,
      "制冷需求日数": 140,
      "舒适日数": 223
    },
    "2020": {
      "供暖需求日数": 4,
      "制冷需求日数": 146,
      "舒适日数": 215
    },
    "2021": {
      "供暖需求日数": 6,
      "制冷需求日数": 159,
      "舒适日数": 200
    },
    "2022": {
      "供暖需求日数": 12,
      "制冷需求日数": 132,
      "舒适日数": 221
    },
    "2023": {
      "供暖需求日数": 10,
      "制冷需求日数": 133,
      "舒适日数": 222
    },
    "2024": {
      "供暖需求日数": 8,
      "制冷需求日数": 133,
      "舒适日数": 224
    },
    "2025": {
      "供暖需求日数": 0,
      "制冷需求日数": 143,
      "舒适日数": 222
    }
  },
  "价值洞察": {
    "数据概览": {
      "数据时间跨度": "2016-01-01 至 2025-12-31",
      "总数据天数": 3653,
      "数据完整性": "完整"
    },
    "核心发现": [
      "温度呈上升趋势：近10年平均温度上升0.18°C，变化率0.81%",
      "最热月份：7月(夏)，平均温度28.89°C",
      "最冷月份：1月(冬)，平均温度15.18°C",
      "极端高温日：0天（超过阈值）",
      "极端低温日：10天（低于阈值）",
      "大温差日：3天（日温差≥15°C）"
    ],
    "应用价值": [
      "1. 农业规划：了解季节性温度模式，优化作物种植时间",
      "2. 能源管理：预测供暖和制冷需求，优化能源消耗",
      "3. 旅游规划：识别最佳旅游季节和极端天气时段",
      "4. 健康预警：识别极端高温/低温时段，发布健康预警",
      "5. 建筑设计：为建筑保温、通风设计提供数据支持",
      "6. 服装零售：预测季节性需求，优化库存管理"
    ],
    "商业价值": [
      "1. 电力需求预测：基于温度数据预测用电高峰，优化电力调度",
      "2. 零售业：根据温度趋势预测季节性商品需求（如空调、取暖设备）",
      "3. 物流运输：识别极端天气时段，优化运输路线和时间",
      "4. 保险业：评估极端天气风险，制定保险费率",
      "5. 房地产：分析气候舒适度，影响房价和租金",
      "6. 农业保险：基于历史极端事件数据，设计保险产品"
    ],
    "研究价值": [
      "1. 气候变化研究：分析长期温度趋势，研究全球变暖影响",
      "2. 气象模式分析：识别季节性模式和异常天气事件",
      "3. 城市热岛效应：对比不同区域数据，研究城市热岛现象",
      "4. 极端天气频率：分析极端事件发生频率和强度变化",
      "5. 机器学习训练：为天气预测模型提供训练数据",
      "6. 环境政策制定：为气候适应政策提供数据支撑"
    ]
  }
}